MLOX/__init__.py
MLOX/add.py
MLOX/subtract.py
IIITBMLOPS-0.0.2.dist-info/LICENSE
IIITBMLOPS-0.0.2.dist-info/METADATA
IIITBMLOPS-0.0.2.dist-info/WHEEL
IIITBMLOPS-0.0.2.dist-info/top_level.txt
IIITBMLOPS-0.0.2.dist-info/RECORD
