Metadata-Version: 2.1
Name: IIITBMLOPS
Version: 0.0.2
Summary: ML operations Library
Home-page: https://github.com/23subbhashit/MLOX/
Author: subbhashit mukherjee
Author-email: subbhashitmukherjee@gmail.com
License: MIT
Requires-Python: >=3.6
License-File: LICENSE
Requires-Dist: numpy (>=1.16.6)
Requires-Dist: pandas (>=1.0.5)
Requires-Dist: seaborn (>=0.10.1)
Requires-Dist: matplotlib (>=3.2.2)
Requires-Dist: scikit-learn (>=0.23.2)
